lightparam/__init__.py
lightparam/core.py
lightparam/param_qt.py
lightparam/param_traits.py
lightparam/utils.py
lightparam/gui/__init__.py
lightparam/gui/collapsible_widget.py
lightparam/gui/controls.py
lightparam/gui/precisionslider.py
lightparam/gui/qt_parametergui.py
lightparam/widgets/__init__.py
lightparam/widgets/trait_widgets.py
lightparam-0.4.6.dist-info/LICENSE.txt
lightparam-0.4.6.dist-info/METADATA
lightparam-0.4.6.dist-info/WHEEL
lightparam-0.4.6.dist-info/top_level.txt
lightparam-0.4.6.dist-info/RECORD
